MANIFEST.in
README.rst
setup.py
main/__init__.py
main/asgi.py
main/disablecsrf.py
main/routing.py
main/settings.py
main/urls.py
tridentstream/__init__.py
tridentstream/apps.py
tridentstream/eventtrack.py
tridentstream/exceptions.py
tridentstream/locktracker.py
tridentstream/models.py
tridentstream/stream.py
tridentstream/testutils.py
tridentstream/utils.py
tridentstream/vfs.py
tridentstream.egg-info/PKG-INFO
tridentstream.egg-info/SOURCES.txt
tridentstream.egg-info/dependency_links.txt
tridentstream.egg-info/requires.txt
tridentstream.egg-info/top_level.txt
tridentstream/bases/__init__.py
tridentstream/bases/listing/__init__.py
tridentstream/bases/listing/apps.py
tridentstream/bases/listing/handler.py
tridentstream/bases/listing/listingbuilder.py
tridentstream/bases/listing/models.py
tridentstream/bases/listing/schema.py
tridentstream/bases/listing/views.py
tridentstream/bases/listing/migrations/0001_initial.py
tridentstream/bases/listing/migrations/__init__.py
tridentstream/bases/metadata/__init__.py
tridentstream/bases/metadata/apps.py
tridentstream/bases/metadata/exceptions.py
tridentstream/bases/metadata/linkingmetadata.py
tridentstream/bases/metadata/mixins.py
tridentstream/bases/metadata/models.py
tridentstream/bases/metadata/remotemetadata.py
tridentstream/bases/metadata/schema.py
tridentstream/bases/websearcher/__init__.py
tridentstream/bases/websearcher/apps.py
tridentstream/bases/websearcher/bencode.py
tridentstream/bases/websearcher/mixins.py
tridentstream/bases/websearcher/models.py
tridentstream/bases/websearcher/schema.py
tridentstream/bases/websearcher/torrentsearcher.py
tridentstream/bases/websearcher/migrations/0001_initial.py
tridentstream/bases/websearcher/migrations/__init__.py
tridentstream/bin/bootstrap-tridentstream
tridentstream/bittorrentclients/__init__.py
tridentstream/bittorrentclients/deluge/__init__.py
tridentstream/bittorrentclients/deluge/apps.py
tridentstream/bittorrentclients/deluge/handler.py
tridentstream/dbs/__init__.py
tridentstream/dbs/leveldb/__init__.py
tridentstream/dbs/leveldb/apps.py
tridentstream/dbs/leveldb/handler.py
tridentstream/dbs/leveldb/tests.py
tridentstream/dbs/lmdb/__init__.py
