Metadata-Version: 2.1
Name: tridentstream
Version: 1.0.8
Summary: Media Streaming Server
Home-page: https://github.com/tridentstream/mediaserver
Author: Anders Jensen
Author-email: johndoee@tridentstream.org
License: MIT
Platform: UNKNOWN
Classifier: Development Status :: 3 - Alpha
Classifier: Environment :: Web Environment
Classifier: Framework :: Twisted
Classifier: Intended Audience :: End Users/Desktop
Classifier: License :: OSI Approved :: MIT License
Classifier: Operating System :: OS Independent
Classifier: Programming Language :: Python
Classifier: Programming Language :: Python :: 3.7
Classifier: Programming Language :: Python :: 3.8
Classifier: Topic :: Internet :: WWW/HTTP
Provides-Extra: lmdb
Provides-Extra: leveldb
Provides-Extra: test
